README.rst
setup.py
nanopack/__init__.py
nanopack/version.py
nanopack.egg-info/PKG-INFO
nanopack.egg-info/SOURCES.txt
nanopack.egg-info/dependency_links.txt
nanopack.egg-info/requires.txt
nanopack.egg-info/top_level.txt